README.md
setup.cfg
setup.py
declaration/__init__.py
declaration/fields.py
declaration/models.py
declaration.egg-info/PKG-INFO
declaration.egg-info/SOURCES.txt
declaration.egg-info/dependency_links.txt
declaration.egg-info/requires.txt
declaration.egg-info/top_level.txt