Metadata-Version: 1.1
Name: declaration
Version: 0.2.3
Summary: Base classes and fields for declarative programming, like Django ORM
Home-page: https://github.com/boomletsgo/declaration
Author: Jordan Ambra
Author-email: jordan@serenitysoftware.io
License: The Unlicense
Keywords: declarative declaration metaclass
Platform: UNKNOWN
Classifier: Development Status :: 5 - Production/Stable
Classifier: Intended Audience :: Developers
Classifier: Operating System :: OS Independent
Classifier: Programming Language :: Python
Classifier: Programming Language :: Python :: 2
Classifier: Programming Language :: Python :: 2.6
Classifier: Programming Language :: Python :: 2.7
Classifier: Programming Language :: Python :: 3
Classifier: Programming Language :: Python :: 3.4
Classifier: Programming Language :: Python :: 3.5
Classifier: Programming Language :: Python :: 3.6
Classifier: Topic :: Software Development :: Libraries
